{
  "comp_id": "baystreet-research",
  "run_date": "2021-02-01",
  "url": "http://baystreetresearch.com/",
  "start_date": "2017-01-01",
  "end_date": "2021-01-01",
  "responses": [
    {
      "Awis": {
        "OperationRequest": {
          "RequestId": "9a1300dd-c1c7-4736-9a9a-fb9cf47b93ef"
        },
        "Results": {
          "Result": {
            "Alexa": {
              "Request": {
                "Arguments": {
                  "Argument": [
                    {
                      "Name": "start",
                      "Value": "20170101"
                    },
                    {
                      "Name": "url",
                      "Value": "http://baystreetresearch.com/\""
                    },
                    {
                      "Name": "responsegroup",
                      "Value": "History"
                    }
                  ]
                }
              },
              "TrafficHistory": {
                "Range": "31",
                "Site": "http://baystreetresearch.com/\"",
                "Start": "2017-01-01",
                "HistoricalData": null
              }
            }
          },
          "ResponseStatus": {
            "StatusCode": "200"
          }
        }
      }
    },
    {
      "Awis": {
        "OperationRequest": {
          "RequestId": "9bb4f6bb-d1b4-4516-931a-6387f3071947"
        },
        "Results": {
          "Result": {
            "Alexa": {
              "Request": {
                "Arguments": {
                  "Argument": [
                    {
                      "Name": "start",
                      "Value": "20170201"
                    },
                    {
                      "Name": "url",
                      "Value": "http://baystreetresearch.com/\""
                    },
                    {
                      "Name": "responsegroup",
                      "Value": "History"
                    }
                  ]
                }
              },
              "TrafficHistory": {
                "Range": "31",
                "Site": "http://baystreetresearch.com/\"",
                "Start": "2017-02-01",
                "HistoricalData": null
              }
            }
          },
          "ResponseStatus": {
            "StatusCode": "200"
          }
        }
      }
    },
    {
      "Awis": {
        "OperationRequest": {
          "RequestId": "b8247fcc-f15d-4d28-ae04-d8f67ac62b12"
        },
        "Results": {
          "Result": {
            "Alexa": {
              "Request": {
                "Arguments": {
                  "Argument": [
                    {
                      "Name": "start",
                      "Value": "20170301"
                    },
                    {
                      "Name": "url",
                      "Value": "http://baystreetresearch.com/\""
                    },
                    {
                      "Name": "responsegroup",
                      "Value": "History"
                    }
                  ]
                }
              },
              "TrafficHistory": {
                "Range": "31",
                "Site": "http://baystreetresearch.com/\"",
                "Start": "2017-03-01",
                "HistoricalData": null
              }
            }
          },
          "ResponseStatus": {
            "StatusCode": "200"
          }
        }
      }
    },
    {
      "Awis": {
        "OperationRequest": {
          "RequestId": "3a7a90ae-24a0-4bd8-9c45-2542a67d4576"
        },
        "Results": {
          "Result": {
            "Alexa": {
              "Request": {
                "Arguments": {
                  "Argument": [
                    {
                      "Name": "start",
                      "Value": "20170401"
                    },
                    {
                      "Name": "url",
                      "Value": "http://baystreetresearch.com/\""
                    },
                    {
                      "Name": "responsegroup",
                      "Value": "History"
                    }
                  ]
                }
              },
              "TrafficHistory": {
                "Range": "31",
                "Site": "http://baystreetresearch.com/\"",
                "Start": "2017-04-01",
                "HistoricalData": null
              }
            }
          },
          "ResponseStatus": {
            "StatusCode": "200"
          }
        }
      }
    },
    {
      "Awis": {
        "OperationRequest": {
          "RequestId": "434a20d9-a39a-4efa-880e-ea89a0c1ffd3"
        },
        "Results": {
          "Result": {
            "Alexa": {
              "Request": {
                "Arguments": {
                  "Argument": [
                    {
                      "Name": "start",
                      "Value": "20170501"
                    },
                    {
                      "Name": "url",
                      "Value": "http://baystreetresearch.com/\""
                    },
                    {
                      "Name": "responsegroup",
                      "Value": "History"
                    }
                  ]
                }
              },
              "TrafficHistory": {
                "Range": "31",
                "Site": "http://baystreetresearch.com/\"",
                "Start": "2017-05-01",
                "HistoricalData": null
              }
            }
          },
          "ResponseStatus": {
            "StatusCode": "200"
          }
        }
      }
    },
    {
      "Awis": {
        "OperationRequest": {
          "RequestId": "22c20d1a-4f77-430c-a3ab-5720ac7a885f"
        },
        "Results": {
          "Result": {
            "Alexa": {
              "Request": {
                "Arguments": {
                  "Argument": [
                    {
                      "Name": "start",
                      "Value": "20170601"
                    },
                    {
                      "Name": "url",
                      "Value": "http://baystreetresearch.com/\""
                    },
                    {
                      "Name": "responsegroup",
                      "Value": "History"
                    }
                  ]
                }
              },
              "TrafficHistory": {
                "Range": "31",
                "Site": "http://baystreetresearch.com/\"",
                "Start": "2017-06-01",
                "HistoricalData": {
                  "Data": {
                    "Date": "2017-06-03",
                    "PageViews": {
                      "PerMillion": "0.02",
                      "PerUser": "1.00"
                    },
                    "Rank": "956830",
                    "Reach": {
                      "PerMillion": "0.7"
                    }
                  }
                }
              }
            }
          },
          "ResponseStatus": {
            "StatusCode": "200"
          }
        }
      }
    },
    {
      "Awis": {
        "OperationRequest": {
          "RequestId": "133b9d50-ed52-4155-acea-2f06b33acb10"
        },
        "Results": {
          "Result": {
            "Alexa": {
              "Request": {
                "Arguments": {
                  "Argument": [
                    {
                      "Name": "start",
                      "Value": "20170701"
                    },
                    {
                      "Name": "url",
                      "Value": "http://baystreetresearch.com/\""
                    },
                    {
                      "Name": "responsegroup",
                      "Value": "History"
                    }
                  ]
                }
              },
              "TrafficHistory": {
                "Range": "31",
                "Site": "http://baystreetresearch.com/\"",
                "Start": "2017-07-01",
                "HistoricalData": null
              }
            }
          },
          "ResponseStatus": {
            "StatusCode": "200"
          }
        }
      }
    },
    {
      "Awis": {
        "OperationRequest": {
          "RequestId": "5e78f6e0-09ec-4350-b134-d103ed8a01bd"
        },
        "Results": {
          "Result": {
            "Alexa": {
              "Request": {
                "Arguments": {
                  "Argument": [
                    {
                      "Name": "start",
                      "Value": "20170801"
                    },
                    {
                      "Name": "url",
                      "Value": "http://baystreetresearch.com/\""
                    },
                    {
                      "Name": "responsegroup",
                      "Value": "History"
                    }
                  ]
                }
              },
              "TrafficHistory": {
                "Range": "31",
                "Site": "http://baystreetresearch.com/\"",
                "Start": "2017-08-01",
                "HistoricalData": null
              }
            }
          },
          "ResponseStatus": {
            "StatusCode": "200"
          }
        }
      }
    },
    {
      "Awis": {
        "OperationRequest": {
          "RequestId": "14dd9343-3406-4daf-ba4f-3eebdd18a3a8"
        },
        "Results": {
          "Result": {
            "Alexa": {
              "Request": {
                "Arguments": {
                  "Argument": [
                    {
                      "Name": "start",
                      "Value": "20170901"
                    },
                    {
                      "Name": "url",
                      "Value": "http://baystreetresearch.com/\""
                    },
                    {
                      "Name": "responsegroup",
                      "Value": "History"
                    }
                  ]
                }
              },
              "TrafficHistory": {
                "Range": "31",
                "Site": "http://baystreetresearch.com/\"",
                "Start": "2017-09-01",
                "HistoricalData": null
              }
            }
          },
          "ResponseStatus": {
            "StatusCode": "200"
          }
        }
      }
    },
    {
      "Awis": {
        "OperationRequest": {
          "RequestId": "cb4e0aed-6572-4919-b0f0-22881dc5912b"
        },
        "Results": {
          "Result": {
            "Alexa": {
              "Request": {
                "Arguments": {
                  "Argument": [
                    {
                      "Name": "start",
                      "Value": "20171001"
                    },
                    {
                      "Name": "url",
                      "Value": "http://baystreetresearch.com/\""
                    },
                    {
                      "Name": "responsegroup",
                      "Value": "History"
                    }
                  ]
                }
              },
              "TrafficHistory": {
                "Range": "31",
                "Site": "http://baystreetresearch.com/\"",
                "Start": "2017-10-01",
                "HistoricalData": {
                  "Data": [
                    {
                      "Date": "2017-10-03",
                      "PageViews": {
                        "PerMillion": "0.04",
                        "PerUser": "3.00"
                      },
                      "Rank": "930994",
                      "Reach": {
                        "PerMillion": "0.6"
                      }
                    },
                    {
                      "Date": "2017-10-13",
                      "PageViews": {
                        "PerMillion": "0.04",
                        "PerUser": "2.00"
                      },
                      "Rank": "766670",
                      "Reach": {
                        "PerMillion": "0.8"
                      }
                    }
                  ]
                }
              }
            }
          },
          "ResponseStatus": {
            "StatusCode": "200"
          }
        }
      }
    },
    {
      "Awis": {
        "OperationRequest": {
          "RequestId": "cdb0c6e1-9ff5-4062-94e0-297ae50c95fb"
        },
        "Results": {
          "Result": {
            "Alexa": {
              "Request": {
                "Arguments": {
                  "Argument": [
                    {
                      "Name": "start",
                      "Value": "20171101"
                    },
                    {
                      "Name": "url",
                      "Value": "http://baystreetresearch.com/\""
                    },
                    {
                      "Name": "responsegroup",
                      "Value": "History"
                    }
                  ]
                }
              },
              "TrafficHistory": {
                "Range": "31",
                "Site": "http://baystreetresearch.com/\"",
                "Start": "2017-11-01",
                "HistoricalData": {
                  "Data": [
                    {
                      "Date": "2017-11-04",
                      "PageViews": {
                        "PerMillion": "0.04",
                        "PerUser": "2.00"
                      },
                      "Rank": "690196",
                      "Reach": {
                        "PerMillion": "0.8"
                      }
                    },
                    {
                      "Date": "2017-11-06",
                      "PageViews": {
                        "PerMillion": "0.06",
                        "PerUser": "5.00"
                      },
                      "Rank": "845626",
                      "Reach": {
                        "PerMillion": "0.6"
                      }
                    }
                  ]
                }
              }
            }
          },
          "ResponseStatus": {
            "StatusCode": "200"
          }
        }
      }
    },
    {
      "Awis": {
        "OperationRequest": {
          "RequestId": "c504281c-0ee2-48fa-ac5d-4665c1bbb64c"
        },
        "Results": {
          "Result": {
            "Alexa": {
              "Request": {
                "Arguments": {
                  "Argument": [
                    {
                      "Name": "start",
                      "Value": "20171201"
                    },
                    {
                      "Name": "url",
                      "Value": "http://baystreetresearch.com/\""
                    },
                    {
                      "Name": "responsegroup",
                      "Value": "History"
                    }
                  ]
                }
              },
              "TrafficHistory": {
                "Range": "31",
                "Site": "http://baystreetresearch.com/\"",
                "Start": "2017-12-01",
                "HistoricalData": null
              }
            }
          },
          "ResponseStatus": {
            "StatusCode": "200"
          }
        }
      }
    },
    {
      "Awis": {
        "OperationRequest": {
          "RequestId": "2ef7f06e-288d-47fb-8a2a-434b61bdf1a4"
        },
        "Results": {
          "Result": {
            "Alexa": {
              "Request": {
                "Arguments": {
                  "Argument": [
                    {
                      "Name": "start",
                      "Value": "20180101"
                    },
                    {
                      "Name": "url",
                      "Value": "http://baystreetresearch.com/\""
                    },
                    {
                      "Name": "responsegroup",
                      "Value": "History"
                    }
                  ]
                }
              },
              "TrafficHistory": {
                "Range": "31",
                "Site": "http://baystreetresearch.com/\"",
                "Start": "2018-01-01",
                "HistoricalData": {
                  "Data": [
                    {
                      "Date": "2018-01-10",
                      "PageViews": {
                        "PerMillion": null,
                        "PerUser": null
                      },
                      "Rank": "1185970",
                      "Reach": {
                        "PerMillion": null
                      }
                    },
                    {
                      "Date": "2018-01-25",
                      "PageViews": {
                        "PerMillion": null,
                        "PerUser": null
                      },
                      "Rank": "1735397",
                      "Reach": {
                        "PerMillion": null
                      }
                    }
                  ]
                }
              }
            }
          },
          "ResponseStatus": {
            "StatusCode": "200"
          }
        }
      }
    },
    {
      "Awis": {
        "OperationRequest": {
          "RequestId": "1ef08e47-cb5f-4ad7-bb79-06b71c797d7c"
        },
        "Results": {
          "Result": {
            "Alexa": {
              "Request": {
                "Arguments": {
                  "Argument": [
                    {
                      "Name": "start",
                      "Value": "20180201"
                    },
                    {
                      "Name": "url",
                      "Value": "http://baystreetresearch.com/\""
                    },
                    {
                      "Name": "responsegroup",
                      "Value": "History"
                    }
                  ]
                }
              },
              "TrafficHistory": {
                "Range": "31",
                "Site": "http://baystreetresearch.com/\"",
                "Start": "2018-02-01",
                "HistoricalData": {
                  "Data": {
                    "Date": "2018-02-15",
                    "PageViews": {
                      "PerMillion": "0.05",
                      "PerUser": "3.00"
                    },
                    "Rank": "759377",
                    "Reach": {
                      "PerMillion": "0.6"
                    }
                  }
                }
              }
            }
          },
          "ResponseStatus": {
            "StatusCode": "200"
          }
        }
      }
    },
    {
      "Awis": {
        "OperationRequest": {
          "RequestId": "f22142ed-d07d-4e52-835d-f49e5e5195ad"
        },
        "Results": {
          "Result": {
            "Alexa": {
              "Request": {
                "Arguments": {
                  "Argument": [
                    {
                      "Name": "start",
                      "Value": "20180301"
                    },
                    {
                      "Name": "url",
                      "Value": "http://baystreetresearch.com/\""
                    },
                    {
                      "Name": "responsegroup",
                      "Value": "History"
                    }
                  ]
                }
              },
              "TrafficHistory": {
                "Range": "31",
                "Site": "http://baystreetresearch.com/\"",
                "Start": "2018-03-01",
                "HistoricalData": null
              }
            }
          },
          "ResponseStatus": {
            "StatusCode": "200"
          }
        }
      }
    },
    {
      "Awis": {
        "OperationRequest": {
          "RequestId": "b9c53057-38f0-4b8b-b4f8-c43a98d91950"
        },
        "Results": {
          "Result": {
            "Alexa": {
              "Request": {
                "Arguments": {
                  "Argument": [
                    {
                      "Name": "start",
                      "Value": "20180401"
                    },
                    {
                      "Name": "url",
                      "Value": "http://baystreetresearch.com/\""
                    },
                    {
                      "Name": "responsegroup",
                      "Value": "History"
                    }
                  ]
                }
              },
              "TrafficHistory": {
                "Range": "31",
                "Site": "http://baystreetresearch.com/\"",
                "Start": "2018-04-01",
                "HistoricalData": null
              }
            }
          },
          "ResponseStatus": {
            "StatusCode": "200"
          }
        }
      }
    },
    {
      "Awis": {
        "OperationRequest": {
          "RequestId": "d35a8a39-56aa-40a3-afdc-6cb743506642"
        },
        "Results": {
          "Result": {
            "Alexa": {
              "Request": {
                "Arguments": {
                  "Argument": [
                    {
                      "Name": "start",
                      "Value": "20180501"
                    },
                    {
                      "Name": "url",
                      "Value": "http://baystreetresearch.com/\""
                    },
                    {
                      "Name": "responsegroup",
                      "Value": "History"
                    }
                  ]
                }
              },
              "TrafficHistory": {
                "Range": "31",
                "Site": "http://baystreetresearch.com/\"",
                "Start": "2018-05-01",
                "HistoricalData": null
              }
            }
          },
          "ResponseStatus": {
            "StatusCode": "200"
          }
        }
      }
    },
    {
      "Awis": {
        "OperationRequest": {
          "RequestId": "4a972592-4935-4dc5-8ff2-a36adcd82f27"
        },
        "Results": {
          "Result": {
            "Alexa": {
              "Request": {
                "Arguments": {
                  "Argument": [
                    {
                      "Name": "start",
                      "Value": "20180601"
                    },
                    {
                      "Name": "url",
                      "Value": "http://baystreetresearch.com/\""
                    },
                    {
                      "Name": "responsegroup",
                      "Value": "History"
                    }
                  ]
                }
              },
              "TrafficHistory": {
                "Range": "31",
                "Site": "http://baystreetresearch.com/\"",
                "Start": "2018-06-01",
                "HistoricalData": null
              }
            }
          },
          "ResponseStatus": {
            "StatusCode": "200"
          }
        }
      }
    },
    {
      "Awis": {
        "OperationRequest": {
          "RequestId": "86c98f7a-0607-4fef-bb2d-fa873b160b3d"
        },
        "Results": {
          "Result": {
            "Alexa": {
              "Request": {
                "Arguments": {
                  "Argument": [
                    {
                      "Name": "start",
                      "Value": "20180701"
                    },
                    {
                      "Name": "url",
                      "Value": "http://baystreetresearch.com/\""
                    },
                    {
                      "Name": "responsegroup",
                      "Value": "History"
                    }
                  ]
                }
              },
              "TrafficHistory": {
                "Range": "31",
                "Site": "http://baystreetresearch.com/\"",
                "Start": "2018-07-01",
                "HistoricalData": null
              }
            }
          },
          "ResponseStatus": {
            "StatusCode": "200"
          }
        }
      }
    },
    {
      "Awis": {
        "OperationRequest": {
          "RequestId": "18bda67b-4c9e-4274-9e81-2861924f132d"
        },
        "Results": {
          "Result": {
            "Alexa": {
              "Request": {
                "Arguments": {
                  "Argument": [
                    {
                      "Name": "start",
                      "Value": "20180801"
                    },
                    {
                      "Name": "url",
                      "Value": "http://baystreetresearch.com/\""
                    },
                    {
                      "Name": "responsegroup",
                      "Value": "History"
                    }
                  ]
                }
              },
              "TrafficHistory": {
                "Range": "31",
                "Site": "http://baystreetresearch.com/\"",
                "Start": "2018-08-01",
                "HistoricalData": null
              }
            }
          },
          "ResponseStatus": {
            "StatusCode": "200"
          }
        }
      }
    },
    {
      "Awis": {
        "OperationRequest": {
          "RequestId": "ce295a9b-3950-4de2-993e-b5c3ec78ed07"
        },
        "Results": {
          "Result": {
            "Alexa": {
              "Request": {
                "Arguments": {
                  "Argument": [
                    {
                      "Name": "start",
                      "Value": "20180901"
                    },
                    {
                      "Name": "url",
                      "Value": "http://baystreetresearch.com/\""
                    },
                    {
                      "Name": "responsegroup",
                      "Value": "History"
                    }
                  ]
                }
              },
              "TrafficHistory": {
                "Range": "31",
                "Site": "http://baystreetresearch.com/\"",
                "Start": "2018-09-01",
                "HistoricalData": null
              }
            }
          },
          "ResponseStatus": {
            "StatusCode": "200"
          }
        }
      }
    },
    {
      "Awis": {
        "OperationRequest": {
          "RequestId": "4d17073d-6164-4292-af37-c3d269f065f7"
        },
        "Results": {
          "Result": {
            "Alexa": {
              "Request": {
                "Arguments": {
                  "Argument": [
                    {
                      "Name": "start",
                      "Value": "20181001"
                    },
                    {
                      "Name": "url",
                      "Value": "http://baystreetresearch.com/\""
                    },
                    {
                      "Name": "responsegroup",
                      "Value": "History"
                    }
                  ]
                }
              },
              "TrafficHistory": {
                "Range": "31",
                "Site": "http://baystreetresearch.com/\"",
                "Start": "2018-10-01",
                "HistoricalData": {
                  "Data": {
                    "Date": "2018-10-25",
                    "PageViews": {
                      "PerMillion": null,
                      "PerUser": null
                    },
                    "Rank": "1000269",
                    "Reach": {
                      "PerMillion": null
                    }
                  }
                }
              }
            }
          },
          "ResponseStatus": {
            "StatusCode": "200"
          }
        }
      }
    },
    {
      "Awis": {
        "OperationRequest": {
          "RequestId": "d892f72c-84f2-40d0-95be-f586f7285ea8"
        },
        "Results": {
          "Result": {
            "Alexa": {
              "Request": {
                "Arguments": {
                  "Argument": [
                    {
                      "Name": "start",
                      "Value": "20181101"
                    },
                    {
                      "Name": "url",
                      "Value": "http://baystreetresearch.com/\""
                    },
                    {
                      "Name": "responsegroup",
                      "Value": "History"
                    }
                  ]
                }
              },
              "TrafficHistory": {
                "Range": "31",
                "Site": "http://baystreetresearch.com/\"",
                "Start": "2018-11-01",
                "HistoricalData": {
                  "Data": [
                    {
                      "Date": "2018-11-07",
                      "PageViews": {
                        "PerMillion": "0.06",
                        "PerUser": "3.00"
                      },
                      "Rank": "630101",
                      "Reach": {
                        "PerMillion": "0.8"
                      }
                    },
                    {
                      "Date": "2018-11-09",
                      "PageViews": {
                        "PerMillion": null,
                        "PerUser": null
                      },
                      "Rank": "1058214",
                      "Reach": {
                        "PerMillion": null
                      }
                    }
                  ]
                }
              }
            }
          },
          "ResponseStatus": {
            "StatusCode": "200"
          }
        }
      }
    },
    {
      "Awis": {
        "OperationRequest": {
          "RequestId": "d8ba8528-ba1f-4db3-a8bd-567a604a8574"
        },
        "Results": {
          "Result": {
            "Alexa": {
              "Request": {
                "Arguments": {
                  "Argument": [
                    {
                      "Name": "start",
                      "Value": "20181201"
                    },
                    {
                      "Name": "url",
                      "Value": "http://baystreetresearch.com/\""
                    },
                    {
                      "Name": "responsegroup",
                      "Value": "History"
                    }
                  ]
                }
              },
              "TrafficHistory": {
                "Range": "31",
                "Site": "http://baystreetresearch.com/\"",
                "Start": "2018-12-01",
                "HistoricalData": null
              }
            }
          },
          "ResponseStatus": {
            "StatusCode": "200"
          }
        }
      }
    },
    {
      "Awis": {
        "OperationRequest": {
          "RequestId": "8a11fc9d-7ce6-4864-b65c-2df732ddf677"
        },
        "Results": {
          "Result": {
            "Alexa": {
              "Request": {
                "Arguments": {
                  "Argument": [
                    {
                      "Name": "start",
                      "Value": "20190101"
                    },
                    {
                      "Name": "url",
                      "Value": "http://baystreetresearch.com/\""
                    },
                    {
                      "Name": "responsegroup",
                      "Value": "History"
                    }
                  ]
                }
              },
              "TrafficHistory": {
                "Range": "31",
                "Site": "http://baystreetresearch.com/\"",
                "Start": "2019-01-01",
                "HistoricalData": null
              }
            }
          },
          "ResponseStatus": {
            "StatusCode": "200"
          }
        }
      }
    },
    {
      "Awis": {
        "OperationRequest": {
          "RequestId": "96ff4ba5-de82-4b88-ae4e-6bd5dc43c1f3"
        },
        "Results": {
          "Result": {
            "Alexa": {
              "Request": {
                "Arguments": {
                  "Argument": [
                    {
                      "Name": "start",
                      "Value": "20190201"
                    },
                    {
                      "Name": "url",
                      "Value": "http://baystreetresearch.com/\""
                    },
                    {
                      "Name": "responsegroup",
                      "Value": "History"
                    }
                  ]
                }
              },
              "TrafficHistory": {
                "Range": "31",
                "Site": "http://baystreetresearch.com/\"",
                "Start": "2019-02-01",
                "HistoricalData": null
              }
            }
          },
          "ResponseStatus": {
            "StatusCode": "200"
          }
        }
      }
    },
    {
      "Awis": {
        "OperationRequest": {
          "RequestId": "498b145c-dc87-4d6e-9451-275cc0aa6988"
        },
        "Results": {
          "Result": {
            "Alexa": {
              "Request": {
                "Arguments": {
                  "Argument": [
                    {
                      "Name": "start",
                      "Value": "20190301"
                    },
                    {
                      "Name": "url",
                      "Value": "http://baystreetresearch.com/\""
                    },
                    {
                      "Name": "responsegroup",
                      "Value": "History"
                    }
                  ]
                }
              },
              "TrafficHistory": {
                "Range": "31",
                "Site": "http://baystreetresearch.com/\"",
                "Start": "2019-03-01",
                "HistoricalData": null
              }
            }
          },
          "ResponseStatus": {
            "StatusCode": "200"
          }
        }
      }
    },
    {
      "Awis": {
        "OperationRequest": {
          "RequestId": "8f66c4bc-cb61-43d1-a129-f8c4d7a75d5d"
        },
        "Results": {
          "Result": {
            "Alexa": {
              "Request": {
                "Arguments": {
                  "Argument": [
                    {
                      "Name": "start",
                      "Value": "20190401"
                    },
                    {
                      "Name": "url",
                      "Value": "http://baystreetresearch.com/\""
                    },
                    {
                      "Name": "responsegroup",
                      "Value": "History"
                    }
                  ]
                }
              },
              "TrafficHistory": {
                "Range": "31",
                "Site": "http://baystreetresearch.com/\"",
                "Start": "2019-04-01",
                "HistoricalData": {
                  "Data": {
                    "Date": "2019-04-13",
                    "PageViews": {
                      "PerMillion": "0.06",
                      "PerUser": "2.00"
                    },
                    "Rank": "552336",
                    "Reach": {
                      "PerMillion": "1"
                    }
                  }
                }
              }
            }
          },
          "ResponseStatus": {
            "StatusCode": "200"
          }
        }
      }
    },
    {
      "Awis": {
        "OperationRequest": {
          "RequestId": "11aa84b1-0b3a-4997-9b49-0133acc0fa75"
        },
        "Results": {
          "Result": {
            "Alexa": {
              "Request": {
                "Arguments": {
                  "Argument": [
                    {
                      "Name": "start",
                      "Value": "20190501"
                    },
                    {
                      "Name": "url",
                      "Value": "http://baystreetresearch.com/\""
                    },
                    {
                      "Name": "responsegroup",
                      "Value": "History"
                    }
                  ]
                }
              },
              "TrafficHistory": {
                "Range": "31",
                "Site": "http://baystreetresearch.com/\"",
                "Start": "2019-05-01",
                "HistoricalData": null
              }
            }
          },
          "ResponseStatus": {
            "StatusCode": "200"
          }
        }
      }
    },
    {
      "Awis": {
        "OperationRequest": {
          "RequestId": "fe091f3e-be99-4091-a0f4-768ac7bf94f8"
        },
        "Results": {
          "Result": {
            "Alexa": {
              "Request": {
                "Arguments": {
                  "Argument": [
                    {
                      "Name": "start",
                      "Value": "20190601"
                    },
                    {
                      "Name": "url",
                      "Value": "http://baystreetresearch.com/\""
                    },
                    {
                      "Name": "responsegroup",
                      "Value": "History"
                    }
                  ]
                }
              },
              "TrafficHistory": {
                "Range": "31",
                "Site": "http://baystreetresearch.com/\"",
                "Start": "2019-06-01",
                "HistoricalData": null
              }
            }
          },
          "ResponseStatus": {
            "StatusCode": "200"
          }
        }
      }
    },
    {
      "Awis": {
        "OperationRequest": {
          "RequestId": "bfe43246-9c62-45ae-991f-048daac81465"
        },
        "Results": {
          "Result": {
            "Alexa": {
              "Request": {
                "Arguments": {
                  "Argument": [
                    {
                      "Name": "start",
                      "Value": "20190701"
                    },
                    {
                      "Name": "url",
                      "Value": "http://baystreetresearch.com/\""
                    },
                    {
                      "Name": "responsegroup",
                      "Value": "History"
                    }
                  ]
                }
              },
              "TrafficHistory": {
                "Range": "31",
                "Site": "http://baystreetresearch.com/\"",
                "Start": "2019-07-01",
                "HistoricalData": {
                  "Data": {
                    "Date": "2019-07-11",
                    "PageViews": {
                      "PerMillion": "0.01",
                      "PerUser": "1.00"
                    },
                    "Rank": "793760",
                    "Reach": {
                      "PerMillion": "0.5"
                    }
                  }
                }
              }
            }
          },
          "ResponseStatus": {
            "StatusCode": "200"
          }
        }
      }
    },
    {
      "Awis": {
        "OperationRequest": {
          "RequestId": "03a4455e-42fe-42e2-8f5f-a26c2c30a806"
        },
        "Results": {
          "Result": {
            "Alexa": {
              "Request": {
                "Arguments": {
                  "Argument": [
                    {
                      "Name": "start",
                      "Value": "20190801"
                    },
                    {
                      "Name": "url",
                      "Value": "http://baystreetresearch.com/\""
                    },
                    {
                      "Name": "responsegroup",
                      "Value": "History"
                    }
                  ]
                }
              },
              "TrafficHistory": {
                "Range": "31",
                "Site": "http://baystreetresearch.com/\"",
                "Start": "2019-08-01",
                "HistoricalData": null
              }
            }
          },
          "ResponseStatus": {
            "StatusCode": "200"
          }
        }
      }
    },
    {
      "Awis": {
        "OperationRequest": {
          "RequestId": "3bbcae41-e0b7-49c1-b48a-3e402cf9a253"
        },
        "Results": {
          "Result": {
            "Alexa": {
              "Request": {
                "Arguments": {
                  "Argument": [
                    {
                      "Name": "start",
                      "Value": "20190901"
                    },
                    {
                      "Name": "url",
                      "Value": "http://baystreetresearch.com/\""
                    },
                    {
                      "Name": "responsegroup",
                      "Value": "History"
                    }
                  ]
                }
              },
              "TrafficHistory": {
                "Range": "31",
                "Site": "http://baystreetresearch.com/\"",
                "Start": "2019-09-01",
                "HistoricalData": null
              }
            }
          },
          "ResponseStatus": {
            "StatusCode": "200"
          }
        }
      }
    },
    {
      "Awis": {
        "OperationRequest": {
          "RequestId": "4a90d12c-f391-4a10-8b70-83fd9bb42784"
        },
        "Results": {
          "Result": {
            "Alexa": {
              "Request": {
                "Arguments": {
                  "Argument": [
                    {
                      "Name": "start",
                      "Value": "20191001"
                    },
                    {
                      "Name": "url",
                      "Value": "http://baystreetresearch.com/\""
                    },
                    {
                      "Name": "responsegroup",
                      "Value": "History"
                    }
                  ]
                }
              },
              "TrafficHistory": {
                "Range": "31",
                "Site": "http://baystreetresearch.com/\"",
                "Start": "2019-10-01",
                "HistoricalData": null
              }
            }
          },
          "ResponseStatus": {
            "StatusCode": "200"
          }
        }
      }
    },
    {
      "Awis": {
        "OperationRequest": {
          "RequestId": "b01fa7d7-15fa-4d52-9881-5f135b01782d"
        },
        "Results": {
          "Result": {
            "Alexa": {
              "Request": {
                "Arguments": {
                  "Argument": [
                    {
                      "Name": "start",
                      "Value": "20191101"
                    },
                    {
                      "Name": "url",
                      "Value": "http://baystreetresearch.com/\""
                    },
                    {
                      "Name": "responsegroup",
                      "Value": "History"
                    }
                  ]
                }
              },
              "TrafficHistory": {
                "Range": "31",
                "Site": "http://baystreetresearch.com/\"",
                "Start": "2019-11-01",
                "HistoricalData": {
                  "Data": {
                    "Date": "2019-11-06",
                    "PageViews": {
                      "PerMillion": "0.1",
                      "PerUser": "2.00"
                    },
                    "Rank": "279445",
                    "Reach": {
                      "PerMillion": "3"
                    }
                  }
                }
              }
            }
          },
          "ResponseStatus": {
            "StatusCode": "200"
          }
        }
      }
    },
    {
      "Awis": {
        "OperationRequest": {
          "RequestId": "a3eeda0b-5575-4fb1-ab82-ad814632ee79"
        },
        "Results": {
          "Result": {
            "Alexa": {
              "Request": {
                "Arguments": {
                  "Argument": [
                    {
                      "Name": "start",
                      "Value": "20191201"
                    },
                    {
                      "Name": "url",
                      "Value": "http://baystreetresearch.com/\""
                    },
                    {
                      "Name": "responsegroup",
                      "Value": "History"
                    }
                  ]
                }
              },
              "TrafficHistory": {
                "Range": "31",
                "Site": "http://baystreetresearch.com/\"",
                "Start": "2019-12-01",
                "HistoricalData": null
              }
            }
          },
          "ResponseStatus": {
            "StatusCode": "200"
          }
        }
      }
    },
    {
      "Awis": {
        "OperationRequest": {
          "RequestId": "d7b7a177-5c5e-4216-91f4-986a475a5241"
        },
        "Results": {
          "Result": {
            "Alexa": {
              "Request": {
                "Arguments": {
                  "Argument": [
                    {
                      "Name": "start",
                      "Value": "20200101"
                    },
                    {
                      "Name": "url",
                      "Value": "http://baystreetresearch.com/\""
                    },
                    {
                      "Name": "responsegroup",
                      "Value": "History"
                    }
                  ]
                }
              },
              "TrafficHistory": {
                "Range": "31",
                "Site": "http://baystreetresearch.com/\"",
                "Start": "2020-01-01",
                "HistoricalData": {
                  "Data": {
                    "Date": "2020-01-30",
                    "PageViews": {
                      "PerMillion": "0.3",
                      "PerUser": "4.00"
                    },
                    "Rank": "254506",
                    "Reach": {
                      "PerMillion": "2"
                    }
                  }
                }
              }
            }
          },
          "ResponseStatus": {
            "StatusCode": "200"
          }
        }
      }
    },
    {
      "Awis": {
        "OperationRequest": {
          "RequestId": "8359630b-f502-4c89-8a11-23d7e521d2fc"
        },
        "Results": {
          "Result": {
            "Alexa": {
              "Request": {
                "Arguments": {
                  "Argument": [
                    {
                      "Name": "start",
                      "Value": "20200201"
                    },
                    {
                      "Name": "url",
                      "Value": "http://baystreetresearch.com/\""
                    },
                    {
                      "Name": "responsegroup",
                      "Value": "History"
                    }
                  ]
                }
              },
              "TrafficHistory": {
                "Range": "31",
                "Site": "http://baystreetresearch.com/\"",
                "Start": "2020-02-01",
                "HistoricalData": null
              }
            }
          },
          "ResponseStatus": {
            "StatusCode": "200"
          }
        }
      }
    },
    {
      "Awis": {
        "OperationRequest": {
          "RequestId": "8a061f33-a5d1-43c5-881b-4a5439610c3b"
        },
        "Results": {
          "Result": {
            "Alexa": {
              "Request": {
                "Arguments": {
                  "Argument": [
                    {
                      "Name": "start",
                      "Value": "20200301"
                    },
                    {
                      "Name": "url",
                      "Value": "http://baystreetresearch.com/\""
                    },
                    {
                      "Name": "responsegroup",
                      "Value": "History"
                    }
                  ]
                }
              },
              "TrafficHistory": {
                "Range": "31",
                "Site": "http://baystreetresearch.com/\"",
                "Start": "2020-03-01",
                "HistoricalData": null
              }
            }
          },
          "ResponseStatus": {
            "StatusCode": "200"
          }
        }
      }
    },
    {
      "Awis": {
        "OperationRequest": {
          "RequestId": "6c8e8ed8-4540-4506-a361-2f4768e2f9c9"
        },
        "Results": {
          "Result": {
            "Alexa": {
              "Request": {
                "Arguments": {
                  "Argument": [
                    {
                      "Name": "start",
                      "Value": "20200401"
                    },
                    {
                      "Name": "url",
                      "Value": "http://baystreetresearch.com/\""
                    },
                    {
                      "Name": "responsegroup",
                      "Value": "History"
                    }
                  ]
                }
              },
              "TrafficHistory": {
                "Range": "31",
                "Site": "http://baystreetresearch.com/\"",
                "Start": "2020-04-01",
                "HistoricalData": null
              }
            }
          },
          "ResponseStatus": {
            "StatusCode": "200"
          }
        }
      }
    },
    {
      "Awis": {
        "OperationRequest": {
          "RequestId": "5d417770-dc05-4fd7-af65-d5062edca779"
        },
        "Results": {
          "Result": {
            "Alexa": {
              "Request": {
                "Arguments": {
                  "Argument": [
                    {
                      "Name": "start",
                      "Value": "20200501"
                    },
                    {
                      "Name": "url",
                      "Value": "http://baystreetresearch.com/\""
                    },
                    {
                      "Name": "responsegroup",
                      "Value": "History"
                    }
                  ]
                }
              },
              "TrafficHistory": {
                "Range": "31",
                "Site": "http://baystreetresearch.com/\"",
                "Start": "2020-05-01",
                "HistoricalData": null
              }
            }
          },
          "ResponseStatus": {
            "StatusCode": "200"
          }
        }
      }
    },
    {
      "Awis": {
        "OperationRequest": {
          "RequestId": "8eff5f3d-c7d8-47d2-91f0-cdb6874360d4"
        },
        "Results": {
          "Result": {
            "Alexa": {
              "Request": {
                "Arguments": {
                  "Argument": [
                    {
                      "Name": "start",
                      "Value": "20200601"
                    },
                    {
                      "Name": "url",
                      "Value": "http://baystreetresearch.com/\""
                    },
                    {
                      "Name": "responsegroup",
                      "Value": "History"
                    }
                  ]
                }
              },
              "TrafficHistory": {
                "Range": "31",
                "Site": "http://baystreetresearch.com/\"",
                "Start": "2020-06-01",
                "HistoricalData": null
              }
            }
          },
          "ResponseStatus": {
            "StatusCode": "200"
          }
        }
      }
    },
    {
      "Awis": {
        "OperationRequest": {
          "RequestId": "76b2e83d-5a64-43c0-9df2-02fd518e268f"
        },
        "Results": {
          "Result": {
            "Alexa": {
              "Request": {
                "Arguments": {
                  "Argument": [
                    {
                      "Name": "start",
                      "Value": "20200701"
                    },
                    {
                      "Name": "url",
                      "Value": "http://baystreetresearch.com/\""
                    },
                    {
                      "Name": "responsegroup",
                      "Value": "History"
                    }
                  ]
                }
              },
              "TrafficHistory": {
                "Range": "31",
                "Site": "http://baystreetresearch.com/\"",
                "Start": "2020-07-01",
                "HistoricalData": null
              }
            }
          },
          "ResponseStatus": {
            "StatusCode": "200"
          }
        }
      }
    },
    {
      "Awis": {
        "OperationRequest": {
          "RequestId": "d83ccaa7-cc25-4c49-9d37-b43f48ae9859"
        },
        "Results": {
          "Result": {
            "Alexa": {
              "Request": {
                "Arguments": {
                  "Argument": [
                    {
                      "Name": "start",
                      "Value": "20200801"
                    },
                    {
                      "Name": "url",
                      "Value": "http://baystreetresearch.com/\""
                    },
                    {
                      "Name": "responsegroup",
                      "Value": "History"
                    }
                  ]
                }
              },
              "TrafficHistory": {
                "Range": "31",
                "Site": "http://baystreetresearch.com/\"",
                "Start": "2020-08-01",
                "HistoricalData": null
              }
            }
          },
          "ResponseStatus": {
            "StatusCode": "200"
          }
        }
      }
    },
    {
      "Awis": {
        "OperationRequest": {
          "RequestId": "08777b0c-2810-451f-af81-35ce9126680f"
        },
        "Results": {
          "Result": {
            "Alexa": {
              "Request": {
                "Arguments": {
                  "Argument": [
                    {
                      "Name": "start",
                      "Value": "20200901"
                    },
                    {
                      "Name": "url",
                      "Value": "http://baystreetresearch.com/\""
                    },
                    {
                      "Name": "responsegroup",
                      "Value": "History"
                    }
                  ]
                }
              },
              "TrafficHistory": {
                "Range": "31",
                "Site": "http://baystreetresearch.com/\"",
                "Start": "2020-09-01",
                "HistoricalData": null
              }
            }
          },
          "ResponseStatus": {
            "StatusCode": "200"
          }
        }
      }
    },
    {
      "Awis": {
        "OperationRequest": {
          "RequestId": "7b2d8ea6-038b-4dd5-93a4-0511551338c7"
        },
        "Results": {
          "Result": {
            "Alexa": {
              "Request": {
                "Arguments": {
                  "Argument": [
                    {
                      "Name": "start",
                      "Value": "20201001"
                    },
                    {
                      "Name": "url",
                      "Value": "http://baystreetresearch.com/\""
                    },
                    {
                      "Name": "responsegroup",
                      "Value": "History"
                    }
                  ]
                }
              },
              "TrafficHistory": {
                "Range": "31",
                "Site": "http://baystreetresearch.com/\"",
                "Start": "2020-10-01",
                "HistoricalData": null
              }
            }
          },
          "ResponseStatus": {
            "StatusCode": "200"
          }
        }
      }
    },
    {
      "Awis": {
        "OperationRequest": {
          "RequestId": "5601de18-1f5d-4b7f-87e4-7185e5eaea9f"
        },
        "Results": {
          "Result": {
            "Alexa": {
              "Request": {
                "Arguments": {
                  "Argument": [
                    {
                      "Name": "start",
                      "Value": "20201101"
                    },
                    {
                      "Name": "url",
                      "Value": "http://baystreetresearch.com/\""
                    },
                    {
                      "Name": "responsegroup",
                      "Value": "History"
                    }
                  ]
                }
              },
              "TrafficHistory": {
                "Range": "31",
                "Site": "http://baystreetresearch.com/\"",
                "Start": "2020-11-01",
                "HistoricalData": null
              }
            }
          },
          "ResponseStatus": {
            "StatusCode": "200"
          }
        }
      }
    },
    {
      "Awis": {
        "OperationRequest": {
          "RequestId": "9fd84d82-96ec-44bc-b024-285a620a1fad"
        },
        "Results": {
          "Result": {
            "Alexa": {
              "Request": {
                "Arguments": {
                  "Argument": [
                    {
                      "Name": "start",
                      "Value": "20201201"
                    },
                    {
                      "Name": "url",
                      "Value": "http://baystreetresearch.com/\""
                    },
                    {
                      "Name": "responsegroup",
                      "Value": "History"
                    }
                  ]
                }
              },
              "TrafficHistory": {
                "Range": "31",
                "Site": "http://baystreetresearch.com/\"",
                "Start": "2020-12-01",
                "HistoricalData": null
              }
            }
          },
          "ResponseStatus": {
            "StatusCode": "200"
          }
        }
      }
    },
    {
      "Awis": {
        "OperationRequest": {
          "RequestId": "5e7ff2da-a702-4a9a-8873-a355f2e4d4f9"
        },
        "Results": {
          "Result": {
            "Alexa": {
              "Request": {
                "Arguments": {
                  "Argument": [
                    {
                      "Name": "start",
                      "Value": "20210101"
                    },
                    {
                      "Name": "url",
                      "Value": "http://baystreetresearch.com/\""
                    },
                    {
                      "Name": "responsegroup",
                      "Value": "History"
                    }
                  ]
                }
              },
              "TrafficHistory": {
                "Range": "30",
                "Site": "http://baystreetresearch.com/\"",
                "Start": "2021-01-01",
                "HistoricalData": null
              }
            }
          },
          "ResponseStatus": {
            "StatusCode": "200"
          }
        }
      }
    }
  ]
}